[
  {
    "en-Us": "SCARLET MACAW",
    "es-Es": "GUACAMAYO ROJO Y AMARILLO O GUACAMAYO MACAO",
    "value": "RED MACAW Y YELLOW MACAW O MACAO MACAW"
  },
  {
    "en-Us": "BLUE AND YELLOW MACAW",
    "es-Es": "GUACAMAYO AZUL Y AMARILLO",
    "value": "BLUE AND YELLOW MACAW"
  },
  {
    "en-Us": "SEVERE MACAW OR LARGE MARACANÁ",
    "es-Es": "GUACAMAYO SEVERO O MARACANÁ GRANDE",
    "value": "SEVERE MACAW OR LARGE MARACANÁ"
  },

  {
    "en-Us": "GREEN MACAW OR MILITARY MACAW",
    "es-Es": "GUACAMAYO VERDE O GUACAMAYO MILITAR",
    "value": "GREEN MACAW OR MILITARY MACAW"
  },
  {
    "en-Us": "LEMON GREEN MACAW",
    "es-Es": "GUACAMAYO VERDE LIMÓN",
    "value": "LEMON GREEN MACAW"
  },
  {
    "en-Us": "RED MACAW",
    "es-Es": "GUACAMAYO ROJO",
    "value": "GUACAMAYO ROJO"
  },
  {
    "en-Us": "RED FRONTED MACAW",
    "es-Es": "GUACAMAYO FRENTE ROJA",
    "value": "RED FRONTED MACAW"
  },
  {
    "en-Us": "NOBLE MACAW OR HAHN'S MACAW",
    "es-Es": "GUACAMAYO NOBLE O GUACAMAYO DE HAHN",
    "value": "NOBLE MACAW OR HAHN'S MACAW"
  },
  {
    "en-Us": "BLUE MACAW OR HYACINTH MACAW",
    "es-Es": "GUACAMAYO AZUL O GUACAMAYO JACINTO",
    "value": "BLUE MACAW OR HYACINTH MACAW"
  },
  {
    "en-Us": "BLUE THROATED MACAW",
    "es-Es": "GUACAMAYO BARBAZUL",
    "value": "BLUE THROATED MACAW"
  }
]
